lycmd/__init__.py
lycmd/login.py
rdconfig/__init__.py
rdconfig/config.py
rdcrm/__init__.py
rdcrm/customer.py
rdcrm/login.py
rdcrm/product.py
rdcrm/salesOrder.py
rdcrm/bill/__init__.py
rdcrm/bill/salesOrder.py
rdcrm/md/__init__.py
rdcrm/md/customer.py
rdcrm/md/product.py
lycmd-1.0.0.dist-info/LICENSE
lycmd-1.0.0.dist-info/METADATA
lycmd-1.0.0.dist-info/WHEEL
lycmd-1.0.0.dist-info/top_level.txt
lycmd-1.0.0.dist-info/RECORD
