Metadata-Version: 2.1
Name: lycmd
Version: 1.0.0
Summary: read config file in py language 
Home-page: http://www.reshapedata.com
Author: hulilei
Author-email: hulilei@takewiki.com.cn
License: Apache License
Keywords: reshapedata,lycmd
Platform: UNKNOWN
Requires-Python: >=3.6
License-File: LICENSE
Requires-Dist: requests
